{
  "dataset_revision": "6cbc1f7b2bc0622f2e39d2c77fa502909748c259",
  "task_name": "StackExchangeClustering.v2",
  "mteb_version": "2.12.32",
  "scores": {
    "test": [
      {
        "v_measures": {
          "Level 0": [
            0.578979,
            0.569164,
            0.554728,
            0.57914,
            0.572576,
            0.581492,
            0.573826,
            0.576602,
            0.574428,
            0.581995
          ]
        },
        "v_measure": 0.574293,
        "v_measure_std": 0.007578,
        "main_score": 0.574293,
        "hf_subset": "default",
        "languages": [
          "eng-Latn"
        ],
        "mteb_version": "2.12.32"
      }
    ]
  },
  "evaluation_time": 246.44873785972595,
  "kg_co2_emissions": null,
  "date": null
}