{
  "dataset_revision": "a9d0821955c418752248b8310438854e56a1cf34",
  "task_name": "CREMA_D",
  "mteb_version": "2.12.32",
  "scores": {
    "train": [
      {
        "scores_per_experiment": [
          {
            "accuracy": 0.269308,
            "f1": 0.25732,
            "f1_weighted": 0.255486,
            "precision": 0.252451,
            "precision_weighted": 0.251183,
            "recall": 0.271785,
            "recall_weighted": 0.269308,
            "ap": null,
            "ap_weighted": null
          },
          {
            "accuracy": 0.298858,
            "f1": 0.290325,
            "f1_weighted": 0.292715,
            "precision": 0.30194,
            "precision_weighted": 0.301383,
            "recall": 0.294535,
            "recall_weighted": 0.298858,
            "ap": null,
            "ap_weighted": null
          },
          {
            "accuracy": 0.278226,
            "f1": 0.273413,
            "f1_weighted": 0.275035,
            "precision": 0.2889,
            "precision_weighted": 0.288989,
            "recall": 0.275545,
            "recall_weighted": 0.278226,
            "ap": null,
            "ap_weighted": null
          },
          {
            "accuracy": 0.329973,
            "f1": 0.316371,
            "f1_weighted": 0.31897,
            "precision": 0.318447,
            "precision_weighted": 0.319707,
            "recall": 0.32578,
            "recall_weighted": 0.329973,
            "ap": null,
            "ap_weighted": null
          },
          {
            "accuracy": 0.272177,
            "f1": 0.262678,
            "f1_weighted": 0.263365,
            "precision": 0.299991,
            "precision_weighted": 0.296304,
            "recall": 0.269985,
            "recall_weighted": 0.272177,
            "ap": null,
            "ap_weighted": null
          }
        ],
        "accuracy": 0.289709,
        "f1": 0.280021,
        "f1_weighted": 0.281114,
        "precision": 0.292346,
        "precision_weighted": 0.291513,
        "recall": 0.287526,
        "recall_weighted": 0.289709,
        "ap": NaN,
        "ap_weighted": NaN,
        "main_score": 0.289709,
        "hf_subset": "default",
        "languages": [
          "eng-Latn"
        ],
        "mteb_version": "2.12.32"
      }
    ]
  },
  "evaluation_time": 2447.0253036022186,
  "kg_co2_emissions": null,
  "date": null
}