{
  "dataset_revision": "96726183040de9e64a590d08eaac8de940dfcbdf",
  "task_name": "DTD",
  "mteb_version": "2.12.32",
  "scores": {
    "test": [
      {
        "scores_per_experiment": [
          {
            "accuracy": 0.756383,
            "f1": 0.743804,
            "f1_weighted": 0.743804,
            "precision": 0.760767,
            "precision_weighted": 0.760767,
            "recall": 0.756383,
            "recall_weighted": 0.756383,
            "ap": null,
            "ap_weighted": null
          },
          {
            "accuracy": 0.76383,
            "f1": 0.753521,
            "f1_weighted": 0.753521,
            "precision": 0.767055,
            "precision_weighted": 0.767055,
            "recall": 0.76383,
            "recall_weighted": 0.76383,
            "ap": null,
            "ap_weighted": null
          },
          {
            "accuracy": 0.754255,
            "f1": 0.742418,
            "f1_weighted": 0.742418,
            "precision": 0.748819,
            "precision_weighted": 0.748819,
            "recall": 0.754255,
            "recall_weighted": 0.754255,
            "ap": null,
            "ap_weighted": null
          },
          {
            "accuracy": 0.758511,
            "f1": 0.743644,
            "f1_weighted": 0.743644,
            "precision": 0.756953,
            "precision_weighted": 0.756953,
            "recall": 0.758511,
            "recall_weighted": 0.758511,
            "ap": null,
            "ap_weighted": null
          },
          {
            "accuracy": 0.755319,
            "f1": 0.74014,
            "f1_weighted": 0.74014,
            "precision": 0.756409,
            "precision_weighted": 0.756409,
            "recall": 0.755319,
            "recall_weighted": 0.755319,
            "ap": null,
            "ap_weighted": null
          }
        ],
        "accuracy": 0.75766,
        "f1": 0.744705,
        "f1_weighted": 0.744705,
        "precision": 0.758,
        "precision_weighted": 0.758,
        "recall": 0.75766,
        "recall_weighted": 0.75766,
        "ap": NaN,
        "ap_weighted": NaN,
        "main_score": 0.75766,
        "hf_subset": "default",
        "languages": [
          "eng-Latn"
        ],
        "mteb_version": "2.12.32"
      }
    ]
  },
  "evaluation_time": 1036.6029641628265,
  "kg_co2_emissions": null,
  "date": null
}